source/CTRW.py
source/FBM.py
source/__init__.py
source/alternating_process.py
source/levy_process.py
source/levy_walk.py
source/multiple_states.py
source/rnd.py
source/trajectory.py
anomalous_diffusion-0.1.0.dist-info/LICENSE
anomalous_diffusion-0.1.0.dist-info/METADATA
anomalous_diffusion-0.1.0.dist-info/WHEEL
anomalous_diffusion-0.1.0.dist-info/top_level.txt
anomalous_diffusion-0.1.0.dist-info/RECORD
